pandaclient/AthenaUtils.py
pandaclient/BookConfig.py
pandaclient/BookGUI.py
pandaclient/Client.py
pandaclient/FileSpec.py
pandaclient/Group_argparse.py
pandaclient/JobSpec.py
pandaclient/LocalJobSpec.py
pandaclient/LocalJobsetSpec.py
pandaclient/MiscUtils.py
pandaclient/MyproxyUtils.py
pandaclient/PBookCore.py
pandaclient/PBookScript.py
pandaclient/PLogger.py
pandaclient/PandaToolsPkgInfo.py
pandaclient/ParseJobXML.py
pandaclient/PathenaScript.py
pandaclient/PchainScript.py
pandaclient/PcontainerScript.py
pandaclient/PdbUtils.py
pandaclient/PhpoScript.py
pandaclient/PrunScript.py
pandaclient/PsubUtils.py
pandaclient/__init__.py
pandaclient/example_task.py
pandaclient/idds_api.py
pandaclient/localSpecs.py
pandaclient/openidc_utils.py
pandaclient/panda_api.py
pandaclient/panda_gui.py
pandaclient/panda_jupyter.py
pandaclient/pcontainer_core.py
pandaclient/queryPandaMonUtils.py
pandaclient/test_client_file.py
pandaclient/test_client_job.py
pandaclient/test_client_misc.py
pandaclient/test_client_submit_job.py
pandaclient/test_client_task.py
pandaclient/time_utils.py
panda_client_light-1.6.8.dist-info/METADATA
panda_client_light-1.6.8.dist-info/WHEEL
panda_client_light-1.6.8.dist-info/licenses/LICENSE
panda_client_light-1.6.8.dist-info/RECORD
