Metadata-Version: 2.4
Name: panda-client-light
Version: 1.6.8
Summary: Lightweight PanDA Client Package installed on PanDA server
Project-URL: Homepage, https://panda-wms.readthedocs.io/en/latest/
Author-email: PanDA Team <panda-support@cern.ch>
License-Expression: Apache-2.0
License-File: LICENSE
Classifier: Programming Language :: Python
Classifier: Programming Language :: Python :: 2
Classifier: Programming Language :: Python :: 2.7
Classifier: Programming Language :: Python :: 3
Classifier: Programming Language :: Python :: 3.5
Classifier: Programming Language :: Python :: 3.6
Classifier: Programming Language :: Python :: 3.7
Classifier: Programming Language :: Python :: 3.8
Classifier: Programming Language :: Python :: 3.9
Classifier: Programming Language :: Python :: 3.10
Classifier: Programming Language :: Python :: 3.11
Requires-Python: !=3.0.*,!=3.1.*,!=3.2.*,!=3.3.*,!=3.4.*,>=2.7
